mcp_server_openai/__init__.py
mcp_server_openai/llm.py
mcp_server_openai/server.py
mcp_server_openai/test_openai.py
mseep_mcp_server_openai-0.1.3.dist-info/licenses/LICENSE
mseep_mcp_server_openai-0.1.3.dist-info/METADATA
mseep_mcp_server_openai-0.1.3.dist-info/WHEEL
mseep_mcp_server_openai-0.1.3.dist-info/entry_points.txt
mseep_mcp_server_openai-0.1.3.dist-info/top_level.txt
mseep_mcp_server_openai-0.1.3.dist-info/RECORD
